rct229/ASHRAE9012019SoftwareTestReport.json
rct229/__init__.py
rct229/cli.py
rct229/report_engine/__init__.py
rct229/report_engine/rct_report.py
rct229/reports/__init__.py
rct229/reports/ashrae9012019/__init__.py
rct229/reports/ashrae9012019/ashrae901_2019_detail_report.py
rct229/reports/ashrae9012019/ashrae901_2019_software_test_report.py
rct229/reports/ashrae9012019/ashrae901_2019_summary_report.py
rct229/reports/ashrae9012022/__init__.py
rct229/reports/ashrae9012022/ashrae901_2022_detail_report.py
rct229/reports/ashrae9012022/ashrae901_2022_software_test_report.py
rct229/reports/ashrae9012022/ashrae901_2022_summary_report.py
rct229/reports/general/__init__.py
rct229/reports/general/engine_raw_output.py
rct229/reports/general/engine_raw_summary.py
rct229/reports/project_report.py
rct229/reports/utils.py
rct229/rule_engine/__init__.py
rct229/rule_engine/engine.py
rct229/rule_engine/memoize.py
rct229/rule_engine/partial_rule_definition.py
rct229/rule_engine/partial_rule_definition_test.py
rct229/rule_engine/rct_outcome_label.py
rct229/rule_engine/rule_base.py
rct229/rule_engine/rule_base_test.py
rct229/rule_engine/rule_list_base.py
rct229/rule_engine/rule_list_indexed_base.py
rct229/rule_engine/ruleset_model_factory.py
rct229/rule_engine/rulesets.py
rct229/rule_engine/tests/test_engine.py
rct229/rule_engine/tests/test_rules.py
rct229/rule_engine/utils.py
rct229/rulesets/__init__.py
rct229/rulesets/ashrae9012019/__init__.py
rct229/rulesets/ashrae9012019/archive/section15/__init__.py
rct229/rulesets/ashrae9012019/archive/section15/section15rule5.py
rct229/rulesets/ashrae9012019/archive/section15/section15rule6.py
rct229/rulesets/ashrae9012019/data/ASHRAE229.9012019.extra.schema-36.json
rct229/rulesets/ashrae9012019/data/ASHRAE229.9012019.extra.schema.json
rct229/rulesets/ashrae9012019/data/ASHRAE229.9012019.extra.schema_0_1_2.json
rct229/rulesets/ashrae9012019/data/ASHRAE229.9012019.extra.schema_0_1_3.json
rct229/rulesets/ashrae9012019/data/__init__.py
ruleset_checking_tool-0.5.0.dist-info/METADATA
ruleset_checking_tool-0.5.0.dist-info/WHEEL
ruleset_checking_tool-0.5.0.dist-info/entry_points.txt
ruleset_checking_tool-0.5.0.dist-info/licenses/LICENSE
ruleset_checking_tool-0.5.0.dist-info/RECORD
