Metadata-Version: 2.4
Name: ruleset-checking-tool
Version: 0.5.0
Summary: PNNL ruleset checking tool
License: MIT
License-File: LICENSE
Author: Weili Xu
Author-email: weili.xu@pnnl.gov
Requires-Python: >=3.10,<4.0
Classifier: License :: OSI Approved :: MIT License
Classifier: Programming Language :: Python :: 3
Classifier: Programming Language :: Python :: 3.10
Classifier: Programming Language :: Python :: 3.11
Classifier: Programming Language :: Python :: 3.12
Classifier: Programming Language :: Python :: 3.13
Classifier: Programming Language :: Python :: 3.14
Provides-Extra: ashrae9012022
Requires-Dist: Pint (>=0.23,<0.24)
Requires-Dist: PyYAML (>=6.0.1,<7.0.0)
Requires-Dist: astor (>=0.8.1,<0.9.0)
Requires-Dist: black (>=22.6.0,<23.0.0)
Requires-Dist: click (>=8.0.4,<9.0.0)
Requires-Dist: jsonpath-ng (>=1.6.1,<2.0.0)
Requires-Dist: jsonpath2 (>=0.4.5,<0.5.0)
Requires-Dist: jsonpointer (>=2.4,<3.0)
Requires-Dist: jsonschema (>=4.21.1,<5.0.0)
Requires-Dist: numpy (>=1.26.4,<2.0.0)
Requires-Dist: openpyxl (>=3.1.2,<4.0.0)
Requires-Dist: pandas (>=2.2.1,<3.0.0)
Requires-Dist: pydash (>=7.0.7,<8.0.0)
Requires-Dist: pyinstrument (>=4.6.2,<5.0.0)
Requires-Dist: regex (>=2022.1.18,<2023.0.0)
Requires-Dist: xlrd (>=1.2,<2.0)
